odoo/addons/pos_return_voucher/README.rst
odoo/addons/pos_return_voucher/__init__.py
odoo/addons/pos_return_voucher/__manifest__.py
odoo/addons/pos_return_voucher/i18n/es.po
odoo/addons/pos_return_voucher/i18n/it.po
odoo/addons/pos_return_voucher/i18n/pos_return_voucher.pot
odoo/addons/pos_return_voucher/models/__init__.py
odoo/addons/pos_return_voucher/models/pos_config.py
odoo/addons/pos_return_voucher/models/pos_order.py
odoo/addons/pos_return_voucher/models/pos_payment.py
odoo/addons/pos_return_voucher/models/pos_payment_method.py
odoo/addons/pos_return_voucher/models/pos_return_voucher.py
odoo/addons/pos_return_voucher/readme/CONFIGURE.rst
odoo/addons/pos_return_voucher/readme/CONTRIBUTORS.rst
odoo/addons/pos_return_voucher/readme/DESCRIPTION.rst
odoo/addons/pos_return_voucher/readme/USAGE.rst
odoo/addons/pos_return_voucher/security/ir.model.access.csv
odoo/addons/pos_return_voucher/static/description/icon.png
odoo/addons/pos_return_voucher/static/description/index.html
odoo/addons/pos_return_voucher/static/description/order-mgmt-icon.png
odoo/addons/pos_return_voucher/static/description/pos-payment-emitted.png
odoo/addons/pos_return_voucher/static/description/pos-payment-validated.png
odoo/addons/pos_return_voucher/static/description/pos-return.png
odoo/addons/pos_return_voucher/static/description/pos-set-return-voucher.png
odoo/addons/pos_return_voucher/static/description/pos_return_voucher-config.png
odoo/addons/pos_return_voucher/static/description/pos_return_voucher-payment-config.png
odoo/addons/pos_return_voucher/static/description/pos_return_voucher-payment-method.png
odoo/addons/pos_return_voucher/static/src/js/PaymentScreen.js
odoo/addons/pos_return_voucher/static/src/js/ReceiptScreen.js
odoo/addons/pos_return_voucher/static/src/js/SetReturnVoucherPopup.js
odoo/addons/pos_return_voucher/static/src/js/models.js
odoo/addons/pos_return_voucher/static/src/xml/OrderReceipt.xml
odoo/addons/pos_return_voucher/static/src/xml/SetReturnVoucherPopup.xml
odoo14_addon_pos_return_voucher-14.0.1.0.1.dev7.dist-info/METADATA
odoo14_addon_pos_return_voucher-14.0.1.0.1.dev7.dist-info/WHEEL
odoo14_addon_pos_return_voucher-14.0.1.0.1.dev7.dist-info/top_level.txt
odoo14_addon_pos_return_voucher-14.0.1.0.1.dev7.dist-info/RECORD
