Metadata-Version: 2.1
Name: odoo14-addon-pos_return_voucher
Version: 14.0.1.0.1.dev7
Summary: Point of Sale - Manage return vouchers
Home-page: https://github.com/OCA/pos
Author: Aures Tic, Odoo Community Association (OCA)
Author-email: support@odoo-community.org
License: AGPL-3
Classifier: Programming Language :: Python
Classifier: Framework :: Odoo
Classifier: Framework :: Odoo :: 14.0
Classifier: License :: OSI Approved :: GNU Affero General Public License v3
Classifier: Development Status :: 3 - Alpha
Requires-Python: >=3.6
Requires-Dist: odoo14-addon-pos-order-mgmt
Requires-Dist: odoo<14.1dev,>=14.0a
